[
  {
    "RACE NUMBER": 81,
    "NAME": "Oscar Piastri",
    "COUNTRY": "Australia",
    "TEAM": "McLaren",
    "GRAND PRIX ENTERED": 63,
    "CAREER POINTS": 713,
    "HIGHEST RACE FINISH": "1 [x9]",
    "PODIUMS": 24,
    "HIGHEST GRID POSITION": "1 [x5]",
    "POLE POSITION": 5,
    "WORLD CHAMPIONSHIPS": 0,
    "DNFs": 4,
    "DATE OF BIRTH": "April 06, 2001",
    "PLACE OF BIRTH": "Melbourne, Victoria",
    "TEXT": "Born in Melbourne, just a stone's throw away from the Australian Grand Prix venue, a young Oscar Piastri's dreams of one day racing in Formula 1 were ignited by the sport's star drivers roaring around his local streets, otherwise known as Albert Park.\n\nBut it would take huge commitment and sacrifice to turn that dream into a reality, with a move to Europe - made by the likes of fellow countrymen Mark Webber and Daniel Ricciardo before him - the only way to go up against the best and catch the attention of the sport's decision-makers.\n\nUsing success on the Australian karting scene as a springboard, Piastri continued to learn the craft in championships across Europe, before getting his first taste of single-seater competition as a 15-year-old - two podium finishes in F4 UAE a sign of things to come.\n\nFrom there, success flowed. British F4 runner-up. Formula Renault champion. F3 champion. F2 champion (by more than 50 points). Piastri did not simply climb the junior single-seater ladder, he charged up it to knock loudly on the F1 door.\n\nSo impressive was Piastri that two F1 teams squabbled over his services for 2023, adding a new dimension to the driver market and so-called 'silly season'. McLaren, and not long-time backers Alpine, won out and their rookie repaid them in spades, taking two podiums in a highly impressive debut campaign.\n\nIt was no flash in the pan. In 2024 Piastri proved vital in McLaren securing their first constructors' title since 1998, pushing more experienced team mate Lando Norris all the way and scoring Grand Prix wins in Hungary and Azerbaijan to finish fourth in the driver standings."
  },
  {
    "RACE NUMBER": 4,
    "NAME": "Lando Norris",
    "COUNTRY": "United Kingdom",
    "TEAM": "McLaren",
    "GRAND PRIX ENTERED": 147,
    "CAREER POINTS": 1339,
    "HIGHEST RACE FINISH": "1 [x9]",
    "PODIUMS": 41,
    "HIGHEST GRID POSITION": "1 [x13]",
    "POLE POSITION": 13,
    "WORLD CHAMPIONSHIPS": 0,
    "DNFs": 13,
    "DATE OF BIRTH": "November 13, 1999",
    "PLACE OF BIRTH": "Bristol, England",
    "TEXT": "Lando Norris may not be named after Star Wars rebel Lando Calrissian - his Mum just liked the moniker - but he has flair and fighting spirit in bountiful supply. \n\nMcLaren had the British teenager on their books for two years before fast-tracking him into F1's galaxy of stars in 2019. A firecracker in his junior career, with a penchant for pole positions and wheel-to-wheel tussles, Norris didn't let them down. \n\nPaired with the highly-rated - and far more experienced - Carlos Sainz, his rookie season was impressive, Norris edging the Spaniard in their head-to-head qualifying battle, scoring points 11 times, and only narrowly missing out on a top-10 championship placing. \n\nA maiden podium came in 2020, with more following in the subsequent two seasons - he narrowly missed out on a win at Russia 2021 - as he dominated another more senior team mate, Daniel Ricciardo, to firmly establish himself in F1's top tier. \n\nIt was the 2024 season that finally brought Norris his breakthrough win - along with three more - as he became the biggest challenger to Max Verstappen's drivers' crown and led McLaren to their first constructors' title since 1998. \n\nAway from the track, Norris brims with a modest charm and an artistic side sees him design and paint his own race gear as a hobby. The focus for the future is allying artistry and ambition on track as McLaren rely on the promise of youth to take them back to the top. \n\nNorris hopes the downforce will be with him…"
  },
  {
    "RACE NUMBER": 63,
    "NAME": "George Russel",
    "COUNTRY": "United Kingdom",
    "TEAM": "Mercedes",
    "GRAND PRIX ENTERED": 147,
    "CAREER POINTS": 996,
    "HIGHEST RACE FINISH": "1 [x5]",
    "PODIUMS": 23,
    "HIGHEST GRID POSITION": "1 [x8]",
    "POLE POSITION": 7,
    "WORLD CHAMPIONSHIPS": 0,
    "DNFs": 19,
    "DATE OF BIRTH": "February 15, 1998",
    "PLACE OF BIRTH": "King's Lynn, England",
    "TEXT": ""
  },
  {
    "RACE NUMBER": 12,
    "NAME": "Kimi Antonelli",
    "COUNTRY": "Italy",
    "TEAM": "Mercedes",
    "GRAND PRIX ENTERED": 19,
    "CAREER POINTS": 89,
    "HIGHEST RACE FINISH": "3 [x1]",
    "PODIUMS": 1,
    "HIGHEST GRID POSITION": "3 [x1]",
    "POLE POSITION": 0,
    "WORLD CHAMPIONSHIPS": 0,
    "DNFs": 4,
    "DATE OF BIRTH": "August 25, 2006",
    "PLACE OF BIRTH": "Bologna, Italy",
    "TEXT": ""
  },
  {
    "RACE NUMBER": 16,
    "NAME": "Charles Leclerc",
    "COUNTRY": "Monaco",
    "TEAM": "Ferrari",
    "GRAND PRIX ENTERED": 166,
    "CAREER POINTS": 1622,
    "HIGHEST RACE FINISH": "1 [x8]",
    "PODIUMS": 49,
    "HIGHEST GRID POSITION": "1 [x27]",
    "POLE POSITION": 27,
    "WORLD CHAMPIONSHIPS": 0,
    "DNFs": 22,
    "DATE OF BIRTH": "October 16, 1997",
    "PLACE OF BIRTH": "Monte Carlo, Monaco",
    "TEXT": ""
  },
  {
    "RACE NUMBER": 44,
    "NAME": "Lewis Hamilton",
    "COUNTRY": "United Kingdom",
    "TEAM": "Ferrari",
    "GRAND PRIX ENTERED": 375,
    "CAREER POINTS": 5004.5,
    "HIGHEST RACE FINISH": "1 [x105]",
    "PODIUMS": 202,
    "HIGHEST GRID POSITION": "1 [x104]",
    "POLE POSITION": 104,
    "WORLD CHAMPIONSHIPS": 7,
    "DNFs": 33,
    "DATE OF BIRTH": "January 7, 1985",
    "PLACE OF BIRTH": "Stevenage, England",
    "TEXT": ""
  },
  {
    "RACE NUMBER": 1,
    "NAME": "Max Verstappen",
    "COUNTRY": "Netherlands",
    "TEAM": "Red Bull Racing",
    "GRAND PRIX ENTERED": 228,
    "CAREER POINTS": 3329.5,
    "HIGHEST RACE FINISH": "1 [x68]",
    "PODIUMS": 122,
    "HIGHEST GRID POSITION": "1 [x47]",
    "POLE POSITION": 47,
    "WORLD CHAMPIONSHIPS": 4,
    "DNFs": 33,
    "DATE OF BIRTH": "September 30, 1997",
    "PLACE OF BIRTH": "Hasselt, Belgium",
    "TEXT": ""
  },
  {
    "RACE NUMBER": 22,
    "NAME": "Yuki Tsunoda",
    "COUNTRY": "Japan",
    "TEAM": "Red Bull Racing",
    "GRAND PRIX ENTERED": 106,
    "CAREER POINTS": 119,
    "HIGHEST RACE FINISH": "4 [x1]",
    "PODIUMS": 0,
    "HIGHEST GRID POSITION": "3 [x1]",
    "POLE POSITION": 0,
    "WORLD CHAMPIONSHIPS": 0,
    "DNFs": 15,
    "DATE OF BIRTH": "May 11, 2000",
    "PLACE OF BIRTH": "Sagamihara, Japan",
    "TEXT": ""
  }
]
